flake8_isort.py
flake8_isort-6.0.0.dist-info/LICENSE
flake8_isort-6.0.0.dist-info/METADATA
flake8_isort-6.0.0.dist-info/WHEEL
flake8_isort-6.0.0.dist-info/entry_points.txt
flake8_isort-6.0.0.dist-info/top_level.txt
flake8_isort-6.0.0.dist-info/RECORD
